{
    "collections": {
        "asia_art_0001": {
            "name": "Asian Art 0001",
            "artworks": [
                "37514.jpg",
                "37755.jpg",
                "38086.jpg",
                "38109.jpg",
                "38363.jpg",
                "39847.jpg",
                "40609.jpg",
                "42486.jpg",
                "50799.jpg",
                "897129.jpg"
            ]
        },
        "asia_art_0002": {
            "name": "Asian Art 0002",
            "artworks": [
                "38322.jpg",
                "39859.jpg",
                "40295.jpg",
                "42413.jpg",
                "42438.jpg",
                "42543.jpg",
                "42703.jpg",
                "44803.jpg",
                "48501.jpg",
                "50898.jpg",
                "61706.jpg",
                "852143.jpg",
                "902223.jpg"
            ]
        },
        "asia_art_0003": {
            "name": "Asian Art 0003",
            "artworks": [
                "37492.jpg",
                "38138.jpg",
                "38254.jpg",
                "39430.jpg",
                "39454.jpg",
                "42135.jpg",
                "42468.jpg",
                "42470.jpg",
                "42695.jpg",
                "45862.jpg",
                "47074.jpg",
                "51937.jpg",
                "52025.jpg",
                "61724.jpg",
                "816473.jpg",
                "837895.jpg",
                "902226.jpg"
            ]
        },
        "asian_art_0004": {
            "name": "Asian Art 0004",
            "artworks": [
                "38237.jpg",
                "38238.jpg",
                "38273.jpg",
                "38600.jpg",
                "39491.jpg",
                "39552.jpg",
                "39676.jpg",
                "39890.jpg",
                "40142.jpg",
                "40454.jpg",
                "42001.jpg",
                "42483.jpg",
                "42716.jpg",
                "44241.jpg",
                "49222.jpg",
                "49946.jpg",
                "49949.jpg",
                "51475.jpg",
                "52955.jpg",
                "53437.jpg",
                "62074.jpg",
                "902217.jpg"
            ]
        },
        "asian_art_0005": {
            "name": "Asian Art 0005",
            "artworks": [
                "39208.jpg",
                "39328.jpg",
                "40143.jpg",
                "40533.jpg",
                "40778.jpg",
                "41911.jpg",
                "42498.jpg",
                "42732.jpg",
                "44068.jpg",
                "44256.jpg",
                "49228.jpg",
                "49370.jpg",
                "49565.jpg",
                "51339.jpg",
                "61235.jpg",
                "61328.jpg",
                "61727.jpg",
                "685283.jpg",
                "78191.jpg"
            ]
        },
        "asian_art_0006": {
            "name": "Asian Art 0006 30EA",
            "artworks": [
                "37498.jpg",
                "37681.jpg",
                "38221.jpg",
                "38245.jpg",
                "38474.jpg",
                "38514.jpg",
                "38716.jpg",
                "39102.jpg",
                "39203.jpg",
                "39268.jpg",
                "40251.jpg",
                "42189.jpg",
                "42238.jpg",
                "42250.jpg",
                "42379.jpg",
                "43306.jpg",
                "44249.jpg",
                "44324.jpg",
                "44615.jpg",
                "44733.jpg",
                "44771.jpg",
                "44800.jpg",
                "49308.jpg",
                "49377.jpg",
                "51343.jpg",
                "56154.jpg",
                "56203.jpg",
                "73805.jpg",
                "78584.jpg",
                "834560.jpg"
            ]
        },
        "asian_art_0007": {
            "name": "Asian Art 0007 30EA",
            "artworks": [
                "37408.jpg",
                "37510.jpg",
                "38282.jpg",
                "39036.jpg",
                "39341.jpg",
                "39386.jpg",
                "39532.jpg",
                "39645.jpg",
                "39839.jpg",
                "39857.jpg",
                "40004.jpg",
                "40746.jpg",
                "42148.jpg",
                "42193.jpg",
                "42315.jpg",
                "42386.jpg",
                "42474.jpg",
                "42717.jpg",
                "44399.jpg",
                "44735.jpg",
                "44893.jpg",
                "49189.jpg",
                "49362.jpg",
                "49568.jpg",
                "50590.jpg",
                "50595.jpg",
                "50716.jpg",
                "51076.jpg",
                "53267.jpg",
                "61838.jpg"
            ]
        },
        "asian_art_0008": {
            "name": "Asian Art 0008 30EA",
            "artworks": [
                "37419.jpg",
                "37650.jpg",
                "37699.jpg",
                "37707.jpg",
                "38222.jpg",
                "38516.jpg",
                "38530.jpg",
                "38986.jpg",
                "39051.jpg",
                "39249.jpg",
                "39345.jpg",
                "40001.jpg",
                "40139.jpg",
                "41336.jpg",
                "41925.jpg",
                "42152.jpg",
                "42180.jpg",
                "42215.jpg",
                "42548.jpg",
                "43801.jpg",
                "44736.jpg",
                "47429.jpg",
                "49566.jpg",
                "50235.jpg",
                "51942.jpg",
                "65348.jpg",
                "713007.jpg",
                "75960.jpg",
                "78187.jpg",
                "838842.jpg"
            ]
        },
        "asian_art_0009": {
            "name": "Asian Art 0009 30EA",
            "artworks": [
                "37427.jpg",
                "37620.jpg",
                "38141.jpg",
                "38169.jpg",
                "38647.jpg",
                "38954.jpg",
                "39047.jpg",
                "39076.jpg",
                "39650.jpg",
                "40770.jpg",
                "42007.jpg",
                "42383.jpg",
                "42725.jpg",
                "48947.jpg",
                "49543.jpg",
                "50121.jpg",
                "50664.jpg",
                "50725.jpg",
                "52713.jpg",
                "53957.jpg",
                "53966.jpg",
                "56221.jpg",
                "56223.jpg",
                "56227.jpg",
                "60602.jpg",
                "61725.jpg",
                "62607.jpg",
                "64920.jpg",
                "65348.jpg",
                "706926.jpg",
                "713007.jpg",
                "75960.jpg",
                "78187.jpg",
                "78192.jpg",
                "838842.jpg"
            ]
        }
    }
}